LICENSE
MANIFEST.in
README.md
setup.py
fspider/VERSION
fspider/__init__.py
fspider/cmdline.py
fspider/context.py
fspider/engine.py
fspider/exceptions.py
fspider/scheduler.py
fspider/server.py
fspider/signals.py
fspider/spider.py
fspider.egg-info/PKG-INFO
fspider.egg-info/SOURCES.txt
fspider.egg-info/dependency_links.txt
fspider.egg-info/entry_points.txt
fspider.egg-info/not-zip-safe
fspider.egg-info/requires.txt
fspider.egg-info/top_level.txt
fspider/commands/__init__.py
fspider/commands/shell.py
fspider/commands/startproject.py
fspider/downloadermiddlewares/__init__.py
fspider/downloadermiddlewares/cookies.py
fspider/downloadermiddlewares/defaultheaders.py
fspider/downloadermiddlewares/down.py
fspider/downloadermiddlewares/downloadtimeout.py
fspider/downloadermiddlewares/retry.py
fspider/downloadermiddlewares/robotstxt.py
fspider/downloadermiddlewares/useragent.py
fspider/http/__init__.py
fspider/http/client.py
fspider/http/downloader.py
fspider/http/headers.py
fspider/http/request.py
fspider/http/response.py
fspider/pipelines/__init__.py
fspider/pipelines/files.py
fspider/pipelines/http.py
fspider/spidermiddlewares/__init__.py
fspider/spidermiddlewares/depth.py
fspider/spidermiddlewares/offsite.py
fspider/spidermiddlewares/referer.py
fspider/templates/project/fspider.cfg.tmpl
fspider/templates/project/main.py.tmpl
fspider/templates/project/module/__init__.py
fspider/templates/project/module/middlewares.py.tmpl
fspider/templates/project/module/pipelines.py.tmpl
fspider/templates/project/module/settings.py.tmpl
fspider/templates/project/module/spiders/__init__.py
fspider/templates/project/module/spiders/test.py
fspider/utils/__init__.py
fspider/utils/asynclib.py
fspider/utils/db.py
fspider/utils/default_settings.py
fspider/utils/middleware.py
fspider/utils/misc.py
fspider/utils/project.py
fspider/utils/reqser.py
fspider/utils/strings.py
fspider/utils/type.py
fspider/utils/url.py