Metadata-Version: 2.1
Name: fspider
Version: 1.1.0
Summary: 基于asyncio异步爬虫网络框架，仿scrapy
Home-page: https://github.com/flagang/fspider
Author: feng
Author-email: 709642236@qq.com
License: MIT
Keywords: async spider
Platform: UNKNOWN
Classifier: License :: OSI Approved :: MIT License
Classifier: Programming Language :: Python
Classifier: Operating System :: OS Independent
Requires-Python: >=3.7
